chanpackage/__init__.py
chanpackage/get_Availability_report.py
chanpackage/googlesheet.py
chanpackage/login_zabbix.py
chanpackage-0.4.dist-info/METADATA
chanpackage-0.4.dist-info/WHEEL
chanpackage-0.4.dist-info/top_level.txt
chanpackage-0.4.dist-info/RECORD
