Metadata-Version: 2.1
Name: chanpackage
Version: 0.4
Summary: insert googlesheet
Home-page: 
Author: channox
Author-email: std3.40160@gmail.com
License: MIT
Requires-Python: >=3.8
Requires-Dist: numpy
Requires-Dist: urllib3
Requires-Dist: requests
Requires-Dist: gspread
Requires-Dist: oauth2client
